pydantic_ai_deepagent/__init__.py
pydantic_ai_deepagent/deepagent.py
pydantic_ai_deepagent/reasoning/__init__.py
pydantic_ai_deepagent/reasoning/_utils.py
pydantic_ai_deepagent/reasoning/deepseek.py
pydantic_ai_deepagent-0.0.3.dist-info/METADATA
pydantic_ai_deepagent-0.0.3.dist-info/WHEEL
pydantic_ai_deepagent-0.0.3.dist-info/licenses/LICENSE
pydantic_ai_deepagent-0.0.3.dist-info/RECORD
