Metadata-Version: 2.4
Name: pydantic_ai_deepagent
Version: 0.0.3
Summary: Reasoning model integration for pydantic-ai's agent
Project-URL: Source, https://github.com/wh1isper/pydantic_ai_deepagent
Author-email: wh1isper <jizhongsheng957@gmail.com>
License: BSD 3-Clause License
License-File: LICENSE
Keywords: pydantic-ai,pydantic_ai_deepagent
Classifier: Programming Language :: Python :: 3
Classifier: Programming Language :: Python :: 3.9
Classifier: Programming Language :: Python :: 3.10
Classifier: Programming Language :: Python :: 3.11
Classifier: Programming Language :: Python :: 3.12
Classifier: Programming Language :: Python :: 3.13
Requires-Python: >=3.9
Requires-Dist: openai
Requires-Dist: pydantic-ai-slim>=0.0.24
Provides-Extra: docs
Requires-Dist: autodoc-pydantic; extra == 'docs'
Requires-Dist: pydata-sphinx-theme; extra == 'docs'
Requires-Dist: sphinx; extra == 'docs'
Requires-Dist: sphinx-click; extra == 'docs'
Provides-Extra: test
Requires-Dist: dirty-equals; extra == 'test'
Requires-Dist: pytest; extra == 'test'
Requires-Dist: pytest-asyncio; extra == 'test'
Requires-Dist: pytest-cov; extra == 'test'
